viu_media/__init__.py
viu_media/__main__.py
viu_media/viu.py
viu_media/assets/normalizer.json
viu_media/assets/defaults/ascii-art
viu_media/assets/defaults/fzf-opts
viu_media/assets/defaults/viu-worker.template.service
viu_media/assets/defaults/rofi-themes/confirm.rasi
viu_media/assets/defaults/rofi-themes/input.rasi
viu_media/assets/defaults/rofi-themes/main.rasi
viu_media/assets/defaults/rofi-themes/preview.rasi
viu_media/assets/graphql/allanime/queries/anime.gql
viu_media/assets/graphql/allanime/queries/episodes.gql
viu_media/assets/graphql/allanime/queries/search.gql
viu_media/assets/graphql/anilist/mutations/delete-list-entry.gql
viu_media/assets/graphql/anilist/mutations/mark-read.gql
viu_media/assets/graphql/anilist/mutations/media-list.gql
viu_media/assets/graphql/anilist/queries/logged-in-user.gql
viu_media/assets/graphql/anilist/queries/media-airing-schedule.gql
viu_media/assets/graphql/anilist/queries/media-characters.gql
viu_media/assets/graphql/anilist/queries/media-list-item.gql
viu_media/assets/graphql/anilist/queries/media-list.gql
viu_media/assets/graphql/anilist/queries/media-recommendations.gql
viu_media/assets/graphql/anilist/queries/media-relations.gql
viu_media/assets/graphql/anilist/queries/notifications.gql
viu_media/assets/graphql/anilist/queries/reviews.gql
viu_media/assets/graphql/anilist/queries/search.gql
viu_media/assets/graphql/anilist/queries/user-info.gql
viu_media/assets/icons/logo.ico
viu_media/assets/icons/logo.png
viu_media/assets/scripts/fzf/_ansi_utils.py
viu_media/assets/scripts/fzf/_filter_parser.py
viu_media/assets/scripts/fzf/airing_schedule_info.py
viu_media/assets/scripts/fzf/character_info.py
viu_media/assets/scripts/fzf/dynamic_preview.py
viu_media/assets/scripts/fzf/episode_info.py
viu_media/assets/scripts/fzf/media_info.py
viu_media/assets/scripts/fzf/preview.py
viu_media/assets/scripts/fzf/review_info.py
viu_media/assets/scripts/fzf/search.py
viu_media/cli/__init__.py
viu_media/cli/cli.py
viu_media/cli/options.py
viu_media-3.3.7.dist-info/METADATA
viu_media-3.3.7.dist-info/WHEEL
viu_media-3.3.7.dist-info/entry_points.txt
viu_media-3.3.7.dist-info/licenses/LICENSE
viu_media-3.3.7.dist-info/RECORD
